mercurial_litf/__init__.py
mercurial_litf/cli.py
mercurial_litf/mercurial_litf.py
mercurial_litf-0.3.0.dist-info/entry_points.txt
mercurial_litf-0.3.0.dist-info/LICENSE
mercurial_litf-0.3.0.dist-info/WHEEL
mercurial_litf-0.3.0.dist-info/METADATA
mercurial_litf-0.3.0.dist-info/RECORD
