Metadata-Version: 2.1
Name: mercurial-litf
Version: 0.3.0
Summary: A litf plugin for the Mercurial test runner
Home-page: https://foss.heptapod.net/mercurial/mercurial-litf
License: MIT
Author: Boris Feld
Author-email: lothiraldan@gmail.com
Requires-Python: >=2.7, !=3.0.*, !=3.1.*, !=3.2.*, !=3.3.*, !=3.4.*, !=3.5.*
Classifier: License :: OSI Approved :: MIT License
Classifier: Programming Language :: Python :: 2
Classifier: Programming Language :: Python :: 2.7
Classifier: Programming Language :: Python :: 3
Classifier: Programming Language :: Python :: 3.6
Classifier: Programming Language :: Python :: 3.7
Classifier: Programming Language :: Python :: 3.8
Classifier: Programming Language :: Python :: 3.9
Project-URL: Repository, https://foss.heptapod.net/mercurial/mercurial-litf
